filgood/__init__.py
filgood/__main__.py
filgood/_version.py
filgood/constants.py
filgood/core.py
filgood/exceptions.py
filgood/pg_dump.py
filgood/py.typed
filgood/structures.py
filgood/utils.py
filgood-0.1.2.dist-info/METADATA
filgood-0.1.2.dist-info/WHEEL
filgood-0.1.2.dist-info/entry_points.txt
filgood-0.1.2.dist-info/licenses/LICENSE
filgood-0.1.2.dist-info/RECORD
