Metadata-Version: 2.4
Name: filgood
Version: 0.1.2
Summary: Fake your PostgreSQL database content with utmost ease using an AI agent
Author-email: Tracktor SAS <sre@tracktor.fr>
Maintainer-email: Tracktor SAS <sre@tracktor.fr>
License-Expression: Apache-2.0
License-File: LICENSE
Classifier: Development Status :: 4 - Beta
Classifier: Environment :: Web Environment
Classifier: Intended Audience :: Developers
Classifier: License :: OSI Approved :: Apache Software License
Classifier: Natural Language :: English
Classifier: Operating System :: OS Independent
Classifier: Programming Language :: Python
Classifier: Programming Language :: Python :: 3
Classifier: Programming Language :: Python :: 3 :: Only
Classifier: Programming Language :: Python :: 3.10
Classifier: Programming Language :: Python :: 3.11
Classifier: Programming Language :: Python :: 3.12
Classifier: Programming Language :: Python :: 3.13
Classifier: Programming Language :: Python :: Implementation :: CPython
Classifier: Topic :: Internet :: WWW/HTTP
Classifier: Topic :: Software Development :: Libraries
Requires-Python: >=3.10
Requires-Dist: aiofile<4,>=3
Requires-Dist: asyncpg<1,>=0.30
Requires-Dist: faker<38,>=37
Requires-Dist: openai<2,>=1
Requires-Dist: piou<1,>=0.16
Requires-Dist: rich<14,>=13
